exploration_stats/__init__.py
exploration_stats-0.0.34.dist-info/METADATA
exploration_stats-0.0.34.dist-info/WHEEL
exploration_stats-0.0.34.dist-info/top_level.txt
exploration_stats-0.0.34.dist-info/RECORD
