Metadata-Version: 2.1
Name: exploration-stats
Version: 0.0.34
Summary: An EDA Package which can perform multiple Eda Operations on your dataframe in one go and yes saves Time as well !!! ------ Developed by Lalit Sharma
Author: Lalit Sharma (Tata Motors)
Author-email: lalit.sharma1@tatamotors.com
License: UNKNOWN
Keywords: python,video,stream,video stream,camera stream,sockets
Platform: UNKNOWN
Classifier: Development Status :: 1 - Planning
Classifier: Intended Audience :: Developers
Classifier: Programming Language :: Python :: 3
Classifier: Operating System :: Unix
Classifier: Operating System :: MacOS :: MacOS X
Classifier: Operating System :: Microsoft :: Windows
Requires-Dist: pandas
Requires-Dist: numpy
Requires-Dist: matplotlib
Requires-Dist: seaborn
Requires-Dist: missingno
Requires-Dist: colorama
